<Properties StartupConfiguration="{6423D166-B0C4-40CF-B88B-65F967E7F7B6}|Default">
  <MultiItemStartupConfigurations />
  <MonoDevelop.Ide.DebuggingService.Breakpoints>
    <BreakpointStore />
  </MonoDevelop.Ide.DebuggingService.Breakpoints>
  <MonoDevelop.Ide.Workbench ActiveDocument="exercise6/Program.cs">
    <Files>
      <File FileName="exercise6/class1.cs" Line="1" Column="1" />
      <File FileName="exercise6/Program.cs" Line="7" Column="19" />
    </Files>
    <Pads>
      <Pad Id="ProjectPad">
        <State name="__root__">
          <Node name="exercise6" expanded="True">
            <Node name="exercise6" expanded="True">
              <Node name="Program.cs" selected="True" />
            </Node>
          </Node>
        </State>
      </Pad>
    </Pads>
  </MonoDevelop.Ide.Workbench>
  <MonoDevelop.Ide.ItemProperties.exercise6 PreferredExecutionTarget="MonoDevelop.Default" />
  <MonoDevelop.Ide.DebuggingService.PinnedWatches />
  <MonoDevelop.Ide.Workspace ActiveConfiguration="Debug" />
</Properties>